AUTHORS.rst
LICENSE.rst
MANIFEST.in
README.rst
setup.py
django_shop_sofortpayment.egg-info/PKG-INFO
django_shop_sofortpayment.egg-info/SOURCES.txt
django_shop_sofortpayment.egg-info/dependency_links.txt
django_shop_sofortpayment.egg-info/not-zip-safe
django_shop_sofortpayment.egg-info/requires.txt
django_shop_sofortpayment.egg-info/top_level.txt
shop_sofortpayment/__init__.py
shop_sofortpayment/admin.py
shop_sofortpayment/conf.py
shop_sofortpayment/gateway.py
shop_sofortpayment/models.py
shop_sofortpayment/locale/de/LC_MESSAGES/django.mo
shop_sofortpayment/locale/de/LC_MESSAGES/django.po
shop_sofortpayment/locale/en/LC_MESSAGES/django.mo
shop_sofortpayment/locale/en/LC_MESSAGES/django.po
shop_sofortpayment/locale/fr/LC_MESSAGES/django.mo
shop_sofortpayment/locale/fr/LC_MESSAGES/django.po
shop_sofortpayment/locale/it/LC_MESSAGES/django.mo
shop_sofortpayment/locale/it/LC_MESSAGES/django.po
shop_sofortpayment/migrations/0001_initial.py
shop_sofortpayment/migrations/0002_auto__add_field_soforttransaction_status__add_field_soforttransaction_.py
shop_sofortpayment/migrations/__init__.py
shop_sofortpayment/templates/shop_sofortpayment/xml/new_transaction.xml
shop_sofortpayment/templates/shop_sofortpayment/xml/transaction_request.xml