Metadata-Version: 1.0
Name: django-shop-sofortpayment
Version: 0.1.3
Summary: A Sofort Bank payment backend for django SHOP
Home-page: https://github.com/piquadrat/django-shop-sofortpayment
Author: Benjamin Wohlwend
Author-email: bw@piquadrat.ch
License: BSD License
Platform: OS Independent
